<!-- views/mass_update_doctor_wizard_views.xml -->
<odoo>
    <!-- Форма для візарда масового оновлення лікаря -->
    <record id="view_mass_update_doctor_wizard" model="ir.ui.view">
        <field name="name">mass.update.doctor.wizard.form</field>
        <field name="model">mass.update.doctor.wizard</field>
        <field name="arch" type="xml">
            <form string="Mass Update Personal Doctor">
                <group>
                    <field name="doctor_id"/>
                </group>
                <footer>
                    <button string="Apply" type="object" name="action_update_doctor" class="btn-primary"/>
                    <button string="Cancel" class="btn-secondary" special="cancel"/>
                </footer>
            </form>
        </field>
    </record>

    <!-- Дія для візарда масового оновлення лікаря -->
    <record id="action_mass_update_doctor_wizard" model="ir.actions.act_window">
        <field name="name">Mass Update Doctor</field>
        <field name="res_model">mass.update.doctor.wizard</field>
        <field name="view_mode">form</field>
        <field name="target">new</field>
        <field name="context">{'active_ids': active_ids}</field>
    </record>

    <!-- Дія для масового оновлення лікаря у перегляді списку пацієнтів -->
    <record id="action_mass_update_doctor" model="ir.actions.server">
        <field name="name">Mass Update Doctor</field>
        <field name="model_id" ref="hr_hospital_lsm.model_hr_hospital_patient"/>
        <field name="binding_model_id" ref="hr_hospital_lsm.model_hr_hospital_patient"/>
        <field name="binding_view_types">list</field>
        <field name="state">code</field>
        <field name="code">
        action = {
            'type': 'ir.actions.act_window',
            'name': 'Mass Update Doctor',
            'res_model': 'mass.update.doctor.wizard',
            'view_mode': 'form',
            'target': 'new',
            'context': {'active_ids': env.context.get('active_ids', [])},
        }
        </field>
    </record>
</odoo>
